<record>
	<id>1507</id>
	<language>ʰMoaekɛ</language>
	<author>Leenhardt (1946)</author>
	<silcode>mkt</silcode>
	<glottocode>vama1243</glottocode>
	<notes>Leenhardt, Maurice. 1946. Langues et dialectes de l'Austro-Mèlanèsie</notes>
	<problems>
Transcription converteⁿd to IPA based on author's phonetic descriptions.

Except: some vowels;
    [r̃] = &quot;dental nasalised liquid&quot;; and
    [’], which I assume to be glottal stop but the author does not explicitly discuss.
</problems>
	<classification>Austronesian, Malayo-Polynesian, Central-Eastern Malayo-Polynesian, Eastern Malayo-Polynesian, Oceanic, Central-Eastern Oceanic, Remote Oceanic, New Caledonian, Northern</classification>
	<typedby>Mary Walworth &amp; John Lynch</typedby>
	<checkedby></checkedby>
	<source>
@book{303461,
  address    = {Paris},
  author     = {Leenhardt, Maurice},
  pages      = {697},
  publisher  = {Institut d'Ethnologie},
  series     = {Travaux et Mémoires de l'Institut d'Ethnologie},
  title      = {Langues et dialectes de l'Austro-Mélanésie},
  volume     = {XLVI},
  year       = {1946},
  besttxt    = {ptxt2papualeenhardt_austro-melanesie1946_o.txt},
  fn         = {papualeenhardt_austro-melanesie1946.pdf, papualeenhardt_austro-melanesie1946pages.pdf, papualeenhardt_austro-melanesie1946_o.pdf},
  hhtype     = {overview;comparative;wordlist;specific_feature},
  inlg       = {French [fra]},
  lgcode     = {Ajië [aji], Arha = Arhâ [aqr], Aro = Arhö [aok], Boewe = Orowe [bpk], Sirhe = Sîshëë [sih], Neku [nek], Ciri = Tiri [cir], Anesu = Xârâcùù [ane], Aragure = Xârâgurè [axx], Dubea = Drubea [duf], Kapone = Numèè [kdk], Pati = Paicî [pri], Camuki = Cemuhî [cam], Pinje = Pije [piz], Poai = Fwâi [fwa], Nemi = Nemi [nem], Wamoang = Waamwang [wmn], Jawe [jaz], Moenebeng = Caac [msq], Yalasu = Balade [NOCODE_Balade], Belep = Belep Nyelâyu [yly], Nenema = Nêlêmwa-Nixumwak [nee], Koumac = Nêlêmwa-Nixumwak [nee], Nua/Bonde = Yuanga [nua], Poapoa = Pwapwâ [pop], Poamei = Pwaamei [pme], Moaveke = Hmwaveke [mrk], Moaeke = Vamale [mkt], Aveke = Haveke [hvk], Aeke = Haeke [aek], Nengone [nen], Iwatenu = Nengone [nen], De'u = Dehu [dhv], Miñ = Dehu [dhv], Iai = Iaai [iai]},
  macro_area = {Papunesia},
  oclc       = {870114007},
  src        = {hh}
}
</source>
</record>

<record>
	<latitude>-20.77080000000000000000</latitude>
	<longitude>165.04000000000000000000</longitude>
</record>

<record>
	<id>337837</id>
	<word_id>1</word_id>
	<word>hand</word>
	<item>i si n</item>
	<annotation></annotation>
	<loan></loan>
	<cognacy>10</cognacy>
	<pmpcognacy></pmpcognacy>
</record>

<record>
	<id>337874</id>
	<word_id>2</word_id>
	<word>left</word>
	<item>jelan poan walaᵐbe</item>
	<annotation></annotation>
	<loan></loan>
	<cognacy>32</cognacy>
	<pmpcognacy></pmpcognacy>
</record>

<record>
	<id>337906</id>
	<word_id>3</word_id>
	<word>right</word>
	<item>jelan poan ji ei</item>
	<annotation></annotation>
	<loan></loan>
	<cognacy></cognacy>
	<pmpcognacy></pmpcognacy>
</record>

<record>
	<id>337947</id>
	<word_id>4</word_id>
	<word>leg/foot</word>
	<item>i xʰa n</item>
	<annotation></annotation>
	<loan></loan>
	<cognacy>1</cognacy>
	<pmpcognacy></pmpcognacy>
</record>

<record>
	<id>337984</id>
	<word_id>5</word_id>
	<word>to walk</word>
	<item>’an</item>
	<annotation></annotation>
	<loan></loan>
	<cognacy>2</cognacy>
	<pmpcognacy></pmpcognacy>
</record>

<record>
	<id>338018</id>
	<word_id>6</word_id>
	<word>road/path</word>
	<item>i foaⁿdan</item>
	<annotation></annotation>
	<loan></loan>
	<cognacy>5,1</cognacy>
	<pmpcognacy></pmpcognacy>
</record>

<record>
	<id>338051</id>
	<word_id>7</word_id>
	<word>to come</word>
	<item>’am</item>
	<annotation></annotation>
	<loan></loan>
	<cognacy>1</cognacy>
	<pmpcognacy></pmpcognacy>
</record>

<record>
	<id>338083</id>
	<word_id>8</word_id>
	<word>to turn</word>
	<item>caguᵐboan</item>
	<annotation></annotation>
	<loan></loan>
	<cognacy></cognacy>
	<pmpcognacy></pmpcognacy>
</record>

<record>
	<id>338115</id>
	<word_id>9</word_id>
	<word>to swim</word>
	<item>t̪om</item>
	<annotation></annotation>
	<loan></loan>
	<cognacy>97</cognacy>
	<pmpcognacy></pmpcognacy>
</record>

<record>
	<id>338148</id>
	<word_id>11</word_id>
	<word>dust</word>
	<item>ʰmun ⁿdop</item>
	<annotation></annotation>
	<loan></loan>
	<cognacy>105,65</cognacy>
	<pmpcognacy></pmpcognacy>
</record>

<record>
	<id>338182</id>
	<word_id>13</word_id>
	<word>back</word>
	<item>i ᵐboan jai n</item>
	<annotation></annotation>
	<loan></loan>
	<cognacy>35, 12</cognacy>
	<pmpcognacy></pmpcognacy>
</record>

<record>
	<id>338216</id>
	<word_id>14</word_id>
	<word>belly</word>
	<item>i jia n</item>
	<annotation></annotation>
	<loan></loan>
	<cognacy>1</cognacy>
	<pmpcognacy></pmpcognacy>
</record>

<record>
	<id>338250</id>
	<word_id>16</word_id>
	<word>intestines</word>
	<item>ni xʰot̪’a n</item>
	<annotation></annotation>
	<loan></loan>
	<cognacy>91</cognacy>
	<pmpcognacy></pmpcognacy>
</record>

<record>
	<id>338284</id>
	<word_id>17</word_id>
	<word>liver</word>
	<item>i xʰi: n</item>
	<annotation></annotation>
	<loan></loan>
	<cognacy>1</cognacy>
	<pmpcognacy></pmpcognacy>
</record>

<record>
	<id>338319</id>
	<word_id>18</word_id>
	<word>breast</word>
	<item>i t̪’i n</item>
	<annotation></annotation>
	<loan></loan>
	<cognacy>1</cognacy>
	<pmpcognacy></pmpcognacy>
</record>

<record>
	<id>338353</id>
	<word_id>19</word_id>
	<word>shoulder</word>
	<item>vin ᵐboaxisi n</item>
	<annotation></annotation>
	<loan></loan>
	<cognacy>65,40</cognacy>
	<pmpcognacy></pmpcognacy>
</record>

<record>
	<id>338386</id>
	<word_id>20</word_id>
	<word>to know, be knowledgeable</word>
	<item>t̪’a ʰnaŋe ke</item>
	<annotation></annotation>
	<loan></loan>
	<cognacy></cognacy>
	<pmpcognacy></pmpcognacy>
</record>

<record>
	<id>338420</id>
	<word_id>21</word_id>
	<word>to think</word>
	<item>ʰmuɲiman</item>
	<annotation></annotation>
	<loan></loan>
	<cognacy>28</cognacy>
	<pmpcognacy></pmpcognacy>
</record>

<record>
	<id>338453</id>
	<word_id>23</word_id>
	<word>blood</word>
	<item>i feⁿdala n</item>
	<annotation></annotation>
	<loan></loan>
	<cognacy>46</cognacy>
	<pmpcognacy></pmpcognacy>
</record>

<record>
	<id>338488</id>
	<word_id>24</word_id>
	<word>head</word>
	<item>ᵐboa n</item>
	<annotation></annotation>
	<loan></loan>
	<cognacy>9</cognacy>
	<pmpcognacy></pmpcognacy>
</record>

<record>
	<id>338522</id>
	<word_id>25</word_id>
	<word>neck</word>
	<item>i ɲo n</item>
	<annotation></annotation>
	<loan></loan>
	<cognacy>18</cognacy>
	<pmpcognacy></pmpcognacy>
</record>

<record>
	<id>338556</id>
	<word_id>26</word_id>
	<word>hair</word>
	<item>ian ᵐboan</item>
	<annotation></annotation>
	<loan></loan>
	<cognacy>4</cognacy>
	<pmpcognacy></pmpcognacy>
</record>

<record>
	<id>338590</id>
	<word_id>27</word_id>
	<word>nose</word>
	<item>ʰpoaⁿdi n</item>
	<annotation></annotation>
	<loan></loan>
	<cognacy>14</cognacy>
	<pmpcognacy></pmpcognacy>
</record>

<record>
	<id>338626</id>
	<word_id>29</word_id>
	<word>to sniff, smell</word>
	<item>t̪ina</item>
	<annotation></annotation>
	<loan></loan>
	<cognacy>116</cognacy>
	<pmpcognacy></pmpcognacy>
</record>

<record>
	<id>338658</id>
	<word_id>30</word_id>
	<word>mouth</word>
	<item>ɲivoa n</item>
	<annotation></annotation>
	<loan></loan>
	<cognacy>36</cognacy>
	<pmpcognacy></pmpcognacy>
</record>

<record>
	<id>338691</id>
	<word_id>31</word_id>
	<word>tooth</word>
	<item>vasĩvoa n</item>
	<annotation></annotation>
	<loan></loan>
	<cognacy>6,1?</cognacy>
	<pmpcognacy></pmpcognacy>
</record>

<record>
	<id>338725</id>
	<word_id>32</word_id>
	<word>tongue</word>
	<item>u ʰpa n</item>
	<annotation></annotation>
	<loan></loan>
	<cognacy>47</cognacy>
	<pmpcognacy></pmpcognacy>
</record>

<record>
	<id>338763</id>
	<word_id>35</word_id>
	<word>to vomit</word>
	<item>muja</item>
	<annotation></annotation>
	<loan></loan>
	<cognacy>1</cognacy>
	<pmpcognacy></pmpcognacy>
</record>

<record>
	<id>338798</id>
	<word_id>37</word_id>
	<word>to eat</word>
	<item>ɣʷiaman</item>
	<annotation></annotation>
	<loan></loan>
	<cognacy>1,55</cognacy>
	<pmpcognacy></pmpcognacy>
</record>

<record>
	<id>338840</id>
	<word_id>40</word_id>
	<word>to drink</word>
	<item>a uⁿdu</item>
	<annotation></annotation>
	<loan></loan>
	<cognacy>6</cognacy>
	<pmpcognacy></pmpcognacy>
</record>

<record>
	<id>338878</id>
	<word_id>42</word_id>
	<word>to suck</word>
	<item>a ⁿdit̪</item>
	<annotation></annotation>
	<loan></loan>
	<cognacy>25</cognacy>
	<pmpcognacy></pmpcognacy>
</record>

<record>
	<id>338911</id>
	<word_id>43</word_id>
	<word>ear</word>
	<item>i jena n</item>
	<annotation></annotation>
	<loan></loan>
	<cognacy>1</cognacy>
	<pmpcognacy></pmpcognacy>
</record>

<record>
	<id>338944</id>
	<word_id>44</word_id>
	<word>to hear</word>
	<item>t̪ina</item>
	<annotation></annotation>
	<loan></loan>
	<cognacy>80</cognacy>
	<pmpcognacy></pmpcognacy>
</record>

<record>
	<id>338976</id>
	<word_id>45</word_id>
	<word>eye</word>
	<item>ɲane man</item>
	<annotation></annotation>
	<loan></loan>
	<cognacy>1</cognacy>
	<pmpcognacy></pmpcognacy>
</record>

<record>
	<id>339017</id>
	<word_id>46</word_id>
	<word>to see</word>
	<item>xaleke</item>
	<annotation></annotation>
	<loan></loan>
	<cognacy>125</cognacy>
	<pmpcognacy></pmpcognacy>
</record>

<record>
	<id>339052</id>
	<word_id>48</word_id>
	<word>to sleep</word>
	<item>meᵐbam</item>
	<annotation></annotation>
	<loan></loan>
	<cognacy></cognacy>
	<pmpcognacy></pmpcognacy>
</record>

<record>
	<id>339083</id>
	<word_id>49</word_id>
	<word>to lie down</word>
	<item>majit̪</item>
	<annotation></annotation>
	<loan></loan>
	<cognacy>37</cognacy>
	<pmpcognacy></pmpcognacy>
</record>

<record>
	<id>339115</id>
	<word_id>50</word_id>
	<word>to dream</word>
	<item>a voa xʰaɲip</item>
	<annotation></annotation>
	<loan></loan>
	<cognacy>1,60</cognacy>
	<pmpcognacy></pmpcognacy>
</record>

<record>
	<id>339148</id>
	<word_id>53</word_id>
	<word>person/human being</word>
	<item>apuli nea</item>
	<annotation></annotation>
	<loan></loan>
	<cognacy>93,95</cognacy>
	<pmpcognacy></pmpcognacy>
</record>

<record>
	<id>339205</id>
	<word_id>54</word_id>
	<word>man/male</word>
	<item>i xaʝu</item>
	<annotation></annotation>
	<loan></loan>
	<cognacy></cognacy>
	<pmpcognacy></pmpcognacy>
</record>

<record>
	<id>339206</id>
	<word_id>54</word_id>
	<word>man/male</word>
	<item>apuli nea</item>
	<annotation></annotation>
	<loan></loan>
	<cognacy></cognacy>
	<pmpcognacy></pmpcognacy>
</record>

<record>
	<id>339269</id>
	<word_id>55</word_id>
	<word>woman/female</word>
	<item>i t̪’amo</item>
	<annotation></annotation>
	<loan></loan>
	<cognacy>119</cognacy>
	<pmpcognacy></pmpcognacy>
</record>

<record>
	<id>339270</id>
	<word_id>55</word_id>
	<word>woman/female</word>
	<item>i moaⁿden</item>
	<annotation></annotation>
	<loan></loan>
	<cognacy>119</cognacy>
	<pmpcognacy></pmpcognacy>
</record>

<record>
	<id>339312</id>
	<word_id>56</word_id>
	<word>child</word>
	<item>i xawe nea</item>
	<annotation></annotation>
	<loan></loan>
	<cognacy></cognacy>
	<pmpcognacy></pmpcognacy>
</record>

<record>
	<id>339344</id>
	<word_id>57</word_id>
	<word>husband</word>
	<item>i xat̪ot̪</item>
	<annotation></annotation>
	<loan></loan>
	<cognacy>2,31</cognacy>
	<pmpcognacy></pmpcognacy>
</record>

<record>
	<id>339380</id>
	<word_id>58</word_id>
	<word>wife</word>
	<item>i xat̪one t̪’amo</item>
	<annotation></annotation>
	<loan></loan>
	<cognacy></cognacy>
	<pmpcognacy></pmpcognacy>
</record>

<record>
	<id>339414</id>
	<word_id>59</word_id>
	<word>mother</word>
	<item>i ɲan</item>
	<annotation></annotation>
	<loan></loan>
	<cognacy>1,83</cognacy>
	<pmpcognacy></pmpcognacy>
</record>

<record>
	<id>339449</id>
	<word_id>60</word_id>
	<word>father</word>
	<item>i jamoa n</item>
	<annotation></annotation>
	<loan></loan>
	<cognacy>1</cognacy>
	<pmpcognacy></pmpcognacy>
</record>

<record>
	<id>339483</id>
	<word_id>61</word_id>
	<word>house</word>
	<item>i moa</item>
	<annotation></annotation>
	<loan></loan>
	<cognacy>1</cognacy>
	<pmpcognacy></pmpcognacy>
</record>

<record>
	<id>339518</id>
	<word_id>62</word_id>
	<word>thatch/roof</word>
	<item>t̪age kon t̪ot̪</item>
	<annotation></annotation>
	<loan></loan>
	<cognacy>20</cognacy>
	<pmpcognacy></pmpcognacy>
</record>

<record>
	<id>339551</id>
	<word_id>64</word_id>
	<word>to say</word>
	<item>avi</item>
	<annotation></annotation>
	<loan></loan>
	<cognacy>13,103</cognacy>
	<pmpcognacy></pmpcognacy>
</record>

<record>
	<id>339584</id>
	<word_id>65</word_id>
	<word>rope</word>
	<item>i o:t̪</item>
	<annotation></annotation>
	<loan></loan>
	<cognacy>31</cognacy>
	<pmpcognacy></pmpcognacy>
</record>

<record>
	<id>339620</id>
	<word_id>68</word_id>
	<word>needle</word>
	<item>i ⁿdu ᵐboa</item>
	<annotation></annotation>
	<loan></loan>
	<cognacy>44</cognacy>
	<pmpcognacy></pmpcognacy>
</record>

<record>
	<id>339654</id>
	<word_id>72</word_id>
	<word>to hit</word>
	<item>can t̪ea</item>
	<annotation></annotation>
	<loan></loan>
	<cognacy>10?</cognacy>
	<pmpcognacy></pmpcognacy>
</record>

<record>
	<id>339692</id>
	<word_id>75</word_id>
	<word>to die, be dead</word>
	<item>mɛ</item>
	<annotation></annotation>
	<loan></loan>
	<cognacy>1</cognacy>
	<pmpcognacy></pmpcognacy>
</record>

<record>
	<id>339732</id>
	<word_id>78</word_id>
	<word>to cut, hack</word>
	<item>t̪’agavi</item>
	<annotation></annotation>
	<loan></loan>
	<cognacy>134</cognacy>
	<pmpcognacy></pmpcognacy>
</record>

<record>
	<id>339771</id>
	<word_id>79</word_id>
	<word>stick/wood</word>
	<item>ʰmuɲan ʝe</item>
	<annotation></annotation>
	<loan></loan>
	<cognacy>46</cognacy>
	<pmpcognacy></pmpcognacy>
</record>

<record>
	<id>339806</id>
	<word_id>84</word_id>
	<word>to plant</word>
	<item>cãmi</item>
	<annotation></annotation>
	<loan></loan>
	<cognacy>73</cognacy>
	<pmpcognacy></pmpcognacy>
</record>

<record>
	<id>339838</id>
	<word_id>85</word_id>
	<word>to choose</word>
	<item>t̪’amui</item>
	<annotation></annotation>
	<loan></loan>
	<cognacy>7</cognacy>
	<pmpcognacy></pmpcognacy>
</record>

<record>
	<id>339869</id>
	<word_id>92</word_id>
	<word>to open, uncover</word>
	<item>t̪aven</item>
	<annotation></annotation>
	<loan></loan>
	<cognacy>37</cognacy>
	<pmpcognacy></pmpcognacy>
</record>

<record>
	<id>339902</id>
	<word_id>93</word_id>
	<word>to pound, beat</word>
	<item>t̪’ake</item>
	<annotation></annotation>
	<loan></loan>
	<cognacy>20</cognacy>
	<pmpcognacy></pmpcognacy>
</record>

<record>
	<id>339940</id>
	<word_id>95</word_id>
	<word>to fall</word>
	<item>sigo</item>
	<annotation></annotation>
	<loan></loan>
	<cognacy>130</cognacy>
	<pmpcognacy></pmpcognacy>
</record>

<record>
	<id>339976</id>
	<word_id>96</word_id>
	<word>dog</word>
	<item>xawakan</item>
	<annotation></annotation>
	<loan></loan>
	<cognacy>43</cognacy>
	<pmpcognacy></pmpcognacy>
</record>

<record>
	<id>340011</id>
	<word_id>97</word_id>
	<word>bird</word>
	<item>i mani</item>
	<annotation></annotation>
	<loan></loan>
	<cognacy>1</cognacy>
	<pmpcognacy></pmpcognacy>
</record>

<record>
	<id>340045</id>
	<word_id>101</word_id>
	<word>to fly</word>
	<item>t̪’en can θoat̪it̪</item>
	<annotation></annotation>
	<loan></loan>
	<cognacy>90</cognacy>
	<pmpcognacy></pmpcognacy>
</record>

<record>
	<id>340091</id>
	<word_id>102</word_id>
	<word>rat</word>
	<item>xʰot̪ap</item>
	<annotation></annotation>
	<loan></loan>
	<cognacy>5</cognacy>
	<pmpcognacy></pmpcognacy>
</record>

<record>
	<id>340092</id>
	<word_id>102</word_id>
	<word>rat</word>
	<item>sine</item>
	<annotation></annotation>
	<loan></loan>
	<cognacy>96</cognacy>
	<pmpcognacy></pmpcognacy>
</record>

<record>
	<id>340135</id>
	<word_id>107</word_id>
	<word>worm (earthworm)</word>
	<item>i ᵐbet̪</item>
	<annotation></annotation>
	<loan></loan>
	<cognacy>11</cognacy>
	<pmpcognacy></pmpcognacy>
</record>

<record>
	<id>340169</id>
	<word_id>109</word_id>
	<word>mosquito</word>
	<item>ɲaᵐbu</item>
	<annotation></annotation>
	<loan></loan>
	<cognacy>1</cognacy>
	<pmpcognacy></pmpcognacy>
</record>

<record>
	<id>340203</id>
	<word_id>110</word_id>
	<word>spider</word>
	<item>saʝo</item>
	<annotation></annotation>
	<loan></loan>
	<cognacy>93</cognacy>
	<pmpcognacy></pmpcognacy>
</record>

<record>
	<id>340237</id>
	<word_id>111</word_id>
	<word>fish</word>
	<item>i ɲu</item>
	<annotation></annotation>
	<loan></loan>
	<cognacy>9</cognacy>
	<pmpcognacy></pmpcognacy>
</record>

<record>
	<id>340271</id>
	<word_id>113</word_id>
	<word>branch</word>
	<item>i ai ŋan</item>
	<annotation></annotation>
	<loan></loan>
	<cognacy></cognacy>
	<pmpcognacy></pmpcognacy>
</record>

<record>
	<id>340305</id>
	<word_id>114</word_id>
	<word>leaf</word>
	<item>i ⁿdon</item>
	<annotation></annotation>
	<loan></loan>
	<cognacy>1</cognacy>
	<pmpcognacy></pmpcognacy>
</record>

<record>
	<id>340340</id>
	<word_id>115</word_id>
	<word>root</word>
	<item>i wa:n</item>
	<annotation></annotation>
	<loan></loan>
	<cognacy>2</cognacy>
	<pmpcognacy></pmpcognacy>
</record>

<record>
	<id>340374</id>
	<word_id>117</word_id>
	<word>fruit</word>
	<item>i ⁿdapoen</item>
	<annotation></annotation>
	<loan></loan>
	<cognacy>1</cognacy>
	<pmpcognacy></pmpcognacy>
</record>

<record>
	<id>340408</id>
	<word_id>119</word_id>
	<word>earth/soil</word>
	<item>ⁿdop</item>
	<annotation></annotation>
	<loan></loan>
	<cognacy>11</cognacy>
	<pmpcognacy></pmpcognacy>
</record>

<record>
	<id>340443</id>
	<word_id>120</word_id>
	<word>stone</word>
	<item>i vai</item>
	<annotation></annotation>
	<loan></loan>
	<cognacy>1</cognacy>
	<pmpcognacy></pmpcognacy>
</record>

<record>
	<id>340477</id>
	<word_id>121</word_id>
	<word>sand</word>
	<item>ʰmewan</item>
	<annotation></annotation>
	<loan></loan>
	<cognacy>31</cognacy>
	<pmpcognacy></pmpcognacy>
</record>

<record>
	<id>340511</id>
	<word_id>122</word_id>
	<word>water</word>
	<item>we</item>
	<annotation></annotation>
	<loan></loan>
	<cognacy>2</cognacy>
	<pmpcognacy></pmpcognacy>
</record>

<record>
	<id>340546</id>
	<word_id>124</word_id>
	<word>sea</word>
	<item>can jat̪i</item>
	<annotation></annotation>
	<loan></loan>
	<cognacy>1</cognacy>
	<pmpcognacy></pmpcognacy>
</record>

<record>
	<id>340580</id>
	<word_id>128</word_id>
	<word>sky</word>
	<item>cana θoat̪it̪</item>
	<annotation></annotation>
	<loan></loan>
	<cognacy>61</cognacy>
	<pmpcognacy></pmpcognacy>
</record>

<record>
	<id>340615</id>
	<word_id>129</word_id>
	<word>moon</word>
	<item>poɛ</item>
	<annotation></annotation>
	<loan></loan>
	<cognacy>52</cognacy>
	<pmpcognacy></pmpcognacy>
</record>

<record>
	<id>340649</id>
	<word_id>130</word_id>
	<word>star</word>
	<item>xʰaʰput̪’in</item>
	<annotation></annotation>
	<loan></loan>
	<cognacy>1?</cognacy>
	<pmpcognacy></pmpcognacy>
</record>

<record>
	<id>340683</id>
	<word_id>131</word_id>
	<word>cloud</word>
	<item>ʰnape θoat̪it̪</item>
	<annotation></annotation>
	<loan></loan>
	<cognacy>85</cognacy>
	<pmpcognacy></pmpcognacy>
</record>

<record>
	<id>340716</id>
	<word_id>133</word_id>
	<word>rain</word>
	<item>ut̪a</item>
	<annotation></annotation>
	<loan></loan>
	<cognacy>1</cognacy>
	<pmpcognacy></pmpcognacy>
</record>

<record>
	<id>340749</id>
	<word_id>134</word_id>
	<word>thunder</word>
	<item>iɣʷala</item>
	<annotation></annotation>
	<loan></loan>
	<cognacy>2</cognacy>
	<pmpcognacy></pmpcognacy>
</record>

<record>
	<id>340782</id>
	<word_id>135</word_id>
	<word>lightning</word>
	<item>mianot̪</item>
	<annotation></annotation>
	<loan></loan>
	<cognacy>15?, 94</cognacy>
	<pmpcognacy></pmpcognacy>
</record>

<record>
	<id>340815</id>
	<word_id>136</word_id>
	<word>wind</word>
	<item>i θat̪</item>
	<annotation></annotation>
	<loan></loan>
	<cognacy>1,66?</cognacy>
	<pmpcognacy></pmpcognacy>
</record>

<record>
	<id>340853</id>
	<word_id>138</word_id>
	<word>warm</word>
	<item>xet̪</item>
	<annotation></annotation>
	<loan></loan>
	<cognacy>109</cognacy>
	<pmpcognacy></pmpcognacy>
</record>

<record>
	<id>340854</id>
	<word_id>138</word_id>
	<word>warm</word>
	<item>sinu’aŋ</item>
	<annotation></annotation>
	<loan></loan>
	<cognacy>11</cognacy>
	<pmpcognacy></pmpcognacy>
</record>

<record>
	<id>340887</id>
	<word_id>139</word_id>
	<word>cold</word>
	<item>xʰim</item>
	<annotation></annotation>
	<loan></loan>
	<cognacy>128</cognacy>
	<pmpcognacy></pmpcognacy>
</record>

<record>
	<id>340920</id>
	<word_id>140</word_id>
	<word>dry</word>
	<item>maiu</item>
	<annotation></annotation>
	<loan></loan>
	<cognacy>1</cognacy>
	<pmpcognacy></pmpcognacy>
</record>

<record>
	<id>340954</id>
	<word_id>141</word_id>
	<word>wet</word>
	<item>foaike</item>
	<annotation></annotation>
	<loan></loan>
	<cognacy>115</cognacy>
	<pmpcognacy></pmpcognacy>
</record>

<record>
	<id>340988</id>
	<word_id>143</word_id>
	<word>fire</word>
	<item>i mae</item>
	<annotation></annotation>
	<loan></loan>
	<cognacy>51</cognacy>
	<pmpcognacy></pmpcognacy>
</record>

<record>
	<id>341022</id>
	<word_id>145</word_id>
	<word>smoke</word>
	<item>ʰmu</item>
	<annotation></annotation>
	<loan></loan>
	<cognacy>2,76</cognacy>
	<pmpcognacy></pmpcognacy>
</record>

<record>
	<id>341056</id>
	<word_id>146</word_id>
	<word>ash</word>
	<item>ⁿdap</item>
	<annotation></annotation>
	<loan></loan>
	<cognacy>1</cognacy>
	<pmpcognacy></pmpcognacy>
</record>

<record>
	<id>341091</id>
	<word_id>147</word_id>
	<word>black</word>
	<item>fiŋ</item>
	<annotation></annotation>
	<loan></loan>
	<cognacy>99</cognacy>
	<pmpcognacy></pmpcognacy>
</record>

<record>
	<id>341127</id>
	<word_id>148</word_id>
	<word>white</word>
	<item>foawat̪</item>
	<annotation></annotation>
	<loan></loan>
	<cognacy>11</cognacy>
	<pmpcognacy></pmpcognacy>
</record>

<record>
	<id>341159</id>
	<word_id>149</word_id>
	<word>red</word>
	<item>t̪ana</item>
	<annotation></annotation>
	<loan></loan>
	<cognacy>2?</cognacy>
	<pmpcognacy></pmpcognacy>
</record>

<record>
	<id>341195</id>
	<word_id>150</word_id>
	<word>yellow</word>
	<item>vaci ⁿdo’aŋ</item>
	<annotation></annotation>
	<loan></loan>
	<cognacy></cognacy>
	<pmpcognacy></pmpcognacy>
</record>

<record>
	<id>341227</id>
	<word_id>151</word_id>
	<word>green</word>
	<item>vun</item>
	<annotation></annotation>
	<loan></loan>
	<cognacy>19?</cognacy>
	<pmpcognacy></pmpcognacy>
</record>

<record>
	<id>341228</id>
	<word_id>151</word_id>
	<word>green</word>
	<item>ᵐbupu</item>
	<annotation></annotation>
	<loan></loan>
	<cognacy>19?</cognacy>
	<pmpcognacy></pmpcognacy>
</record>

<record>
	<id>341260</id>
	<word_id>152</word_id>
	<word>small</word>
	<item>ju ɣʷat̪in</item>
	<annotation></annotation>
	<loan></loan>
	<cognacy></cognacy>
	<pmpcognacy></pmpcognacy>
</record>

<record>
	<id>341293</id>
	<word_id>153</word_id>
	<word>big</word>
	<item>xapoen</item>
	<annotation></annotation>
	<loan></loan>
	<cognacy>14</cognacy>
	<pmpcognacy></pmpcognacy>
</record>

<record>
	<id>341328</id>
	<word_id>156</word_id>
	<word>thin</word>
	<item>aleⁿdep</item>
	<annotation></annotation>
	<loan></loan>
	<cognacy>63</cognacy>
	<pmpcognacy></pmpcognacy>
</record>

<record>
	<id>341360</id>
	<word_id>157</word_id>
	<word>thick</word>
	<item>t̪’aᵐbo</item>
	<annotation></annotation>
	<loan></loan>
	<cognacy>70</cognacy>
	<pmpcognacy></pmpcognacy>
</record>

<record>
	<id>341395</id>
	<word_id>160</word_id>
	<word>painful, sick</word>
	<item>sinu</item>
	<annotation></annotation>
	<loan></loan>
	<cognacy>106?</cognacy>
	<pmpcognacy></pmpcognacy>
</record>

<record>
	<id>341396</id>
	<word_id>160</word_id>
	<word>painful, sick</word>
	<item>mɛ</item>
	<annotation></annotation>
	<loan></loan>
	<cognacy>1</cognacy>
	<pmpcognacy></pmpcognacy>
</record>

<record>
	<id>341442</id>
	<word_id>162</word_id>
	<word>old</word>
	<item>en a pa xaumu</item>
	<annotation></annotation>
	<loan></loan>
	<cognacy>64</cognacy>
	<pmpcognacy></pmpcognacy>
</record>

<record>
	<id>341479</id>
	<word_id>163</word_id>
	<word>new</word>
	<item>en aᵐboa xaʰmaŋ</item>
	<annotation></annotation>
	<loan></loan>
	<cognacy>53</cognacy>
	<pmpcognacy></pmpcognacy>
</record>

<record>
	<id>341512</id>
	<word_id>164</word_id>
	<word>good</word>
	<item>xaʰnaŋ</item>
	<annotation></annotation>
	<loan></loan>
	<cognacy>136,137</cognacy>
	<pmpcognacy></pmpcognacy>
</record>

<record>
	<id>341546</id>
	<word_id>165</word_id>
	<word>bad, evil</word>
	<item>ɲau</item>
	<annotation></annotation>
	<loan></loan>
	<cognacy></cognacy>
	<pmpcognacy></pmpcognacy>
</record>

<record>
	<id>341580</id>
	<word_id>166</word_id>
	<word>correct, true</word>
	<item>jukeju</item>
	<annotation></annotation>
	<loan></loan>
	<cognacy>99</cognacy>
	<pmpcognacy></pmpcognacy>
</record>

<record>
	<id>341614</id>
	<word_id>167</word_id>
	<word>night</word>
	<item>ᵐboen</item>
	<annotation></annotation>
	<loan></loan>
	<cognacy>1</cognacy>
	<pmpcognacy></pmpcognacy>
</record>

<record>
	<id>341648</id>
	<word_id>168</word_id>
	<word>day</word>
	<item>θoat̪it̪</item>
	<annotation></annotation>
	<loan></loan>
	<cognacy>51</cognacy>
	<pmpcognacy></pmpcognacy>
</record>

<record>
	<id>341683</id>
	<word_id>170</word_id>
	<word>when?</word>
	<item>ɲet̪</item>
	<annotation></annotation>
	<loan></loan>
	<cognacy>78</cognacy>
	<pmpcognacy></pmpcognacy>
</record>

<record>
	<id>341723</id>
	<word_id>174</word_id>
	<word>in, inside</word>
	<item>can</item>
	<annotation></annotation>
	<loan></loan>
	<cognacy>15</cognacy>
	<pmpcognacy></pmpcognacy>
</record>

<record>
	<id>341755</id>
	<word_id>179</word_id>
	<word>near</word>
	<item>a pat̪emoano</item>
	<annotation></annotation>
	<loan></loan>
	<cognacy>113</cognacy>
	<pmpcognacy></pmpcognacy>
</record>

<record>
	<id>341790</id>
	<word_id>180</word_id>
	<word>far</word>
	<item>a’o:t̪</item>
	<annotation></annotation>
	<loan></loan>
	<cognacy>97</cognacy>
	<pmpcognacy></pmpcognacy>
</record>

<record>
	<id>341826</id>
	<word_id>181</word_id>
	<word>where?</word>
	<item>a ave</item>
	<annotation></annotation>
	<loan></loan>
	<cognacy>3</cognacy>
	<pmpcognacy></pmpcognacy>
</record>

<record>
	<id>341862</id>
	<word_id>182</word_id>
	<word>I</word>
	<item>o</item>
	<annotation></annotation>
	<loan></loan>
	<cognacy>1</cognacy>
	<pmpcognacy></pmpcognacy>
</record>

<record>
	<id>341895</id>
	<word_id>183</word_id>
	<word>thou</word>
	<item>ko</item>
	<annotation></annotation>
	<loan></loan>
	<cognacy>1</cognacy>
	<pmpcognacy></pmpcognacy>
</record>

<record>
	<id>341927</id>
	<word_id>184</word_id>
	<word>he/she</word>
	<item>kon</item>
	<annotation></annotation>
	<loan></loan>
	<cognacy>1</cognacy>
	<pmpcognacy></pmpcognacy>
</record>

<record>
	<id>341928</id>
	<word_id>184</word_id>
	<word>he/she</word>
	<item>ke</item>
	<annotation></annotation>
	<loan></loan>
	<cognacy>1</cognacy>
	<pmpcognacy></pmpcognacy>
</record>

<record>
	<id>341981</id>
	<word_id>185</word_id>
	<word>we</word>
	<item>ga</item>
	<annotation></annotation>
	<loan></loan>
	<cognacy></cognacy>
	<pmpcognacy></pmpcognacy>
</record>

<record>
	<id>341982</id>
	<word_id>185</word_id>
	<word>we</word>
	<item>ᵐbe</item>
	<annotation></annotation>
	<loan></loan>
	<cognacy></cognacy>
	<pmpcognacy></pmpcognacy>
</record>

<record>
	<id>342018</id>
	<word_id>186</word_id>
	<word>you</word>
	<item>gae</item>
	<annotation></annotation>
	<loan></loan>
	<cognacy>1</cognacy>
	<pmpcognacy></pmpcognacy>
</record>

<record>
	<id>342048</id>
	<word_id>187</word_id>
	<word>they</word>
	<item>le</item>
	<annotation></annotation>
	<loan></loan>
	<cognacy>1,70</cognacy>
	<pmpcognacy></pmpcognacy>
</record>

<record>
	<id>342049</id>
	<word_id>187</word_id>
	<word>they</word>
	<item>ke</item>
	<annotation></annotation>
	<loan></loan>
	<cognacy>1,69</cognacy>
	<pmpcognacy></pmpcognacy>
</record>

<record>
	<id>342089</id>
	<word_id>188</word_id>
	<word>what?</word>
	<item>i ⁿda</item>
	<annotation></annotation>
	<loan></loan>
	<cognacy>1</cognacy>
	<pmpcognacy></pmpcognacy>
</record>

<record>
	<id>342119</id>
	<word_id>192</word_id>
	<word>and</word>
	<item>go</item>
	<annotation></annotation>
	<loan></loan>
	<cognacy>12</cognacy>
	<pmpcognacy></pmpcognacy>
</record>

<record>
	<id>342120</id>
	<word_id>192</word_id>
	<word>and</word>
	<item>ᵐboa</item>
	<annotation></annotation>
	<loan></loan>
	<cognacy>2</cognacy>
	<pmpcognacy></pmpcognacy>
</record>

<record>
	<id>342152</id>
	<word_id>193</word_id>
	<word>if</word>
	<item>cama</item>
	<annotation></annotation>
	<loan></loan>
	<cognacy>26,3</cognacy>
	<pmpcognacy></pmpcognacy>
</record>

<record>
	<id>342185</id>
	<word_id>195</word_id>
	<word>no, not</word>
	<item>cika</item>
	<annotation></annotation>
	<loan></loan>
	<cognacy>10,83</cognacy>
	<pmpcognacy></pmpcognacy>
</record>

<record>
	<id>342218</id>
	<word_id>196</word_id>
	<word>to count</word>
	<item>fine</item>
	<annotation></annotation>
	<loan></loan>
	<cognacy>26</cognacy>
	<pmpcognacy></pmpcognacy>
</record>

<record>
	<id>342256</id>
	<word_id>197</word_id>
	<word>One</word>
	<item>se</item>
	<annotation></annotation>
	<loan></loan>
	<cognacy>14</cognacy>
	<pmpcognacy></pmpcognacy>
</record>

<record>
	<id>342290</id>
	<word_id>198</word_id>
	<word>Two</word>
	<item>t̪alo</item>
	<annotation></annotation>
	<loan></loan>
	<cognacy>1</cognacy>
	<pmpcognacy></pmpcognacy>
</record>

<record>
	<id>342324</id>
	<word_id>199</word_id>
	<word>Three</word>
	<item>t̪’ien</item>
	<annotation></annotation>
	<loan></loan>
	<cognacy>1</cognacy>
	<pmpcognacy></pmpcognacy>
</record>

<record>
	<id>342358</id>
	<word_id>200</word_id>
	<word>Four</word>
	<item>fava</item>
	<annotation></annotation>
	<loan></loan>
	<cognacy>1,65 </cognacy>
	<pmpcognacy></pmpcognacy>
</record>

<record>
	<id>342392</id>
	<word_id>201</word_id>
	<word>Five</word>
	<item>nim</item>
	<annotation></annotation>
	<loan></loan>
	<cognacy>1,15</cognacy>
	<pmpcognacy></pmpcognacy>
</record>

<record>
	<id>342426</id>
	<word_id>202</word_id>
	<word>Six</word>
	<item>nim ᵐboa se</item>
	<annotation></annotation>
	<loan></loan>
	<cognacy></cognacy>
	<pmpcognacy></pmpcognacy>
</record>

<record>
	<id>342459</id>
	<word_id>203</word_id>
	<word>Seven</word>
	<item>nim ᵐboa t̪’alo</item>
	<annotation></annotation>
	<loan></loan>
	<cognacy></cognacy>
	<pmpcognacy></pmpcognacy>
</record>

<record>
	<id>342493</id>
	<word_id>204</word_id>
	<word>Eight</word>
	<item>nim ᵐboa t̪’ien</item>
	<annotation></annotation>
	<loan></loan>
	<cognacy></cognacy>
	<pmpcognacy></pmpcognacy>
</record>

<record>
	<id>342526</id>
	<word_id>205</word_id>
	<word>Nine</word>
	<item>nim ᵐboa fava</item>
	<annotation></annotation>
	<loan></loan>
	<cognacy></cognacy>
	<pmpcognacy></pmpcognacy>
</record>

<record>
	<id>342561</id>
	<word_id>206</word_id>
	<word>Ten</word>
	<item>vajilu</item>
	<annotation></annotation>
	<loan></loan>
	<cognacy>12</cognacy>
	<pmpcognacy></pmpcognacy>
</record>

<record>
	<id>342592</id>
	<word_id>207</word_id>
	<word>Twenty</word>
	<item>se apuli</item>
	<annotation></annotation>
	<loan></loan>
	<cognacy></cognacy>
	<pmpcognacy></pmpcognacy>
</record>

<record>
	<id>342622</id>
	<word_id>209</word_id>
	<word>One Hundred</word>
	<item>nim apuli</item>
	<annotation></annotation>
	<loan></loan>
	<cognacy></cognacy>
	<pmpcognacy></pmpcognacy>
</record>

